prime_cli/__init__.py
prime_cli/config.py
prime_cli/main.py
prime_cli/py.typed
prime_cli/api/__init__.py
prime_cli/api/availability.py
prime_cli/api/client.py
prime_cli/api/pods.py
prime_cli/api/sandbox.py
prime_cli/commands/__init__.py
prime_cli/commands/availability.py
prime_cli/commands/config.py
prime_cli/commands/env.py
prime_cli/commands/login.py
prime_cli/commands/pods.py
prime_cli/commands/sandbox.py
prime_cli/helper/__init__.py
prime_cli/helper/short_id.py
prime_cli-0.3.8.dist-info/METADATA
prime_cli-0.3.8.dist-info/WHEEL
prime_cli-0.3.8.dist-info/entry_points.txt
prime_cli-0.3.8.dist-info/licenses/LICENSE
prime_cli-0.3.8.dist-info/RECORD
