Metadata-Version: 2.4
Name: prime-cli
Version: 0.3.8
Summary: Prime Intellect CLI
Project-URL: Homepage, https://github.com/PrimeIntellect-ai/prime-cli
Project-URL: Documentation, https://github.com/PrimeIntellect-ai/prime-cli#readme
Project-URL: Repository, https://github.com/PrimeIntellect-ai/prime-cli.git
Project-URL: Changelog, https://github.com/PrimeIntellect-ai/prime-cli/blob/main/CHANGELOG.md
Author-email: Prime Intellect <contact@primeintellect.ai>
License-Expression: MIT
License-File: LICENSE
Keywords: cli,cloud,compute,gpu
Classifier: Development Status :: 4 - Beta
Classifier: Environment :: Console
Classifier: Intended Audience :: Developers
Classifier: License :: OSI Approved :: MIT License
Classifier: Operating System :: OS Independent
Classifier: Programming Language :: Python :: 3
Classifier: Programming Language :: Python :: 3.11
Classifier: Programming Language :: Python :: 3.12
Classifier: Topic :: Software Development :: Libraries :: Python Modules
Requires-Python: <3.13,>=3.11
Requires-Dist: build>=1.0.0
Requires-Dist: cryptography>=41.0.0
Requires-Dist: pydantic>=2.0.0
Requires-Dist: requests>=2.31.0
Requires-Dist: rich>=13.3.1
Requires-Dist: toml>=0.10.0
Requires-Dist: typer>=0.9.0
Requires-Dist: verifiers>=0.1.2.post0
Provides-Extra: dev
Requires-Dist: mypy>=1.8.0; extra == 'dev'
Requires-Dist: pre-commit>=3.5.0; extra == 'dev'
Requires-Dist: pytest>=7.0.0; extra == 'dev'
Requires-Dist: ruff>=0.1.8; extra == 'dev'
Requires-Dist: types-requests>=2.31.0; extra == 'dev'
Requires-Dist: types-toml>=0.10.0; extra == 'dev'
